EncryptedHTTP/__init__.py
EncryptedHTTP/client.py
EncryptedHTTP/server.py
EncryptedHTTP/server_utils.py
EncryptedHTTP-1.0.0.dist-info/LICENSE
EncryptedHTTP-1.0.0.dist-info/METADATA
EncryptedHTTP-1.0.0.dist-info/WHEEL
EncryptedHTTP-1.0.0.dist-info/top_level.txt
EncryptedHTTP-1.0.0.dist-info/RECORD
