Metadata-Version: 2.1
Name: EncryptedHTTP
Version: 1.0.0
Summary: A secure encrypted way for a flask server to communicate to a local client without HTTPS.
Author-email: Evscion <ivoscev@example.com>
Project-URL: Homepage, https://github.com/EncryptedHTTP
Project-URL: Bug Tracker, https://github.com/Evscion/EncryptedHTTP/issues
Classifier: Programming Language :: Python :: 3
Classifier: License :: OSI Approved :: MIT License
Classifier: Operating System :: OS Independent
Requires-Python: >=3.7
License-File: LICENSE
